xsoar_cli/__about__.py
xsoar_cli/__init__.py
xsoar_cli/cli.py
xsoar_cli/configuration.py
xsoar_cli/utilities.py
xsoar_cli/case/README.md
xsoar_cli/case/__init__.py
xsoar_cli/case/commands.py
xsoar_cli/config/README.md
xsoar_cli/config/__init__.py
xsoar_cli/config/commands.py
xsoar_cli/graph/README.md
xsoar_cli/graph/__init__.py
xsoar_cli/graph/commands.py
xsoar_cli/manifest/README.md
xsoar_cli/manifest/__init__.py
xsoar_cli/manifest/commands.py
xsoar_cli/pack/README.md
xsoar_cli/pack/__init__.py
xsoar_cli/pack/commands.py
xsoar_cli/playbook/README.md
xsoar_cli/playbook/__init__.py
xsoar_cli/playbook/commands.py
xsoar_cli/plugins/README.md
xsoar_cli/plugins/__init__.py
xsoar_cli/plugins/commands.py
xsoar_cli/plugins/manager.py
xsoar_cli-1.0.10.dist-info/METADATA
xsoar_cli-1.0.10.dist-info/WHEEL
xsoar_cli-1.0.10.dist-info/entry_points.txt
xsoar_cli-1.0.10.dist-info/licenses/LICENSE.txt
xsoar_cli-1.0.10.dist-info/RECORD
