Metadata-Version: 2.4
Name: xsoar-cli
Version: 1.0.10
Project-URL: Documentation, https://github.com/tlium/xsoar-cli#readme
Project-URL: Issues, https://github.com/tlium/xsoar-cli/issues
Project-URL: Source, https://github.com/tlium/xsoar-cli
Author-email: Torbjørn Lium <torben@lium.org>
License-Expression: MIT
License-File: LICENSE.txt
Classifier: Development Status :: 4 - Beta
Classifier: Programming Language :: Python
Classifier: Programming Language :: Python :: 3.10
Classifier: Programming Language :: Python :: 3.11
Classifier: Programming Language :: Python :: 3.12
Classifier: Programming Language :: Python :: Implementation :: CPython
Classifier: Programming Language :: Python :: Implementation :: PyPy
Requires-Python: <3.13,>=3.10
Requires-Dist: click==8.1.8
Requires-Dist: pyyaml>=6.0.2
Requires-Dist: xsoar-client>=2.0.0
Requires-Dist: xsoar-dependency-graph>=0.0.3
